{
  "id": "R91818",
  "category": "gigiena",
  "name": "Атоми Гигиенические прокладки из натурального хлопка (Ночные)",
  "badge": "",
  "priceBefore": 1100,
  "priceAfter": 1000,
  "inStock": false,
  "city_stock": false,
  "buyHidden": false,
  "photoCount": 5,
  "tags": [],
  "desc": "Материал обладает великолепными впитывающими свойствами и хорошо подстраивается под формы тела, обеспечивая комфорт. Натуральный состав не содержит пластик, красители, искуственные ароматизаторы, синтетические волокна и отбеливатели.",
  "manufacturerCode": "R91818",
  "siteCode": "R91818",
  "manufacturerUrl": "https://www.atomy.ru/product/R91818"
}